LICENSE
MANIFEST.in
README.md
requirements.txt
setup.py
quantiphyse_t1/__init__.py
quantiphyse_t1/_version.py
quantiphyse_t1/process.py
quantiphyse_t1/t10.png
quantiphyse_t1/t10_fabber.png
quantiphyse_t1/t1_model.cpp
quantiphyse_t1/t1_model.pyx
quantiphyse_t1/tests.py
quantiphyse_t1/widgets.py
quantiphyse_t1.egg-info/PKG-INFO
quantiphyse_t1.egg-info/SOURCES.txt
quantiphyse_t1.egg-info/dependency_links.txt
quantiphyse_t1.egg-info/entry_points.txt
quantiphyse_t1.egg-info/requires.txt
quantiphyse_t1.egg-info/top_level.txt
quantiphyse_t1/src/T10_calculation.cpp
quantiphyse_t1/src/T10_calculation.h
quantiphyse_t1/src/linear_regression.cpp
quantiphyse_t1/src/linear_regression.h
quantiphyse_t1/src/test/example.cpp