Metadata-Version: 2.1
Name: quantiphyse-t1
Version: 0.9.1
Summary: Quantiphyse plugin for Bayesian T1 mapping
Home-page: https://quantiphyse.readthedocs.io/
Author: Martin Craig
Author-email: martin.craig@eng.ox.ac.uk
License: License granted by University of Oxford for use by academics carrying out research and not for use by consumers or commercial businesses. See LICENSE file for more details
Platform: UNKNOWN
Classifier: Development Status :: 3 - Alpha
Classifier: Intended Audience :: Science/Research
Classifier: Programming Language :: Python :: 2.7
Classifier: Programming Language :: Python :: 3
Classifier: Topic :: Scientific/Engineering :: Bio-Informatics
Classifier: License :: Free for non-commercial use
